nonebot/adapters/satori/__init__.py
nonebot/adapters/satori/adapter.py
nonebot/adapters/satori/bot.py
nonebot/adapters/satori/config.py
nonebot/adapters/satori/element.py
nonebot/adapters/satori/event.py
nonebot/adapters/satori/exception.py
nonebot/adapters/satori/message.py
nonebot/adapters/satori/models.py
nonebot/adapters/satori/utils.py
nonebot_adapter_satori-0.13.7.dist-info/METADATA
nonebot_adapter_satori-0.13.7.dist-info/WHEEL
nonebot_adapter_satori-0.13.7.dist-info/entry_points.txt
nonebot_adapter_satori-0.13.7.dist-info/licenses/LICENSE
nonebot_adapter_satori-0.13.7.dist-info/RECORD
