Metadata-Version: 2.1
Name: nonebot-adapter-satori
Version: 0.13.7
Summary: Satori Protocol Adapter for Nonebot2
Author-Email: RF-Tar-Railt <rf_tar_railt@qq.com>
License: MIT
Project-URL: homepage, https://github.com/nonebot/adapter-satori
Project-URL: repository, https://github.com/nonebot/adapter-satori
Requires-Python: >=3.9
Requires-Dist: nonebot2>=2.4.2
